<?xml version="1.0" encoding="UTF-8" ?>
  <customers>
    <data>
      <name>Kelsey Attisha</name>
      <hobby>Dance</hobby>
      <age>25</age>
      <gender>F</gender>
      <city>Seattle</city>
      <country>US</country>
    </data>
    <data>
      <name>Sean Beckwith</name>
      <hobby>Fishing</hobby>
      <age>30</age>
      <gender>M</gender>
      <city>Seattle</city>
      <country>US</country>
    </data>
    <data>
      <name>Ying Cai</name>
      <hobby>Board Game</hobby>
      <age>27</age>
      <gender>F</gender>
      <city>Shang Hai</city>
      <country>China</country>
    </data>
    <data>
      <name>Samia Bhatti</name>
      <hobby>Cooking</hobby>
      <age>24</age>
      <gender>F</gender>
      <city>New York</city>
      <country>US</country>
    </data>
    <data>
      <name>Michael Cardinal</name>
      <hobby>Reading</hobby>
      <age>32</age>
      <gender>M</gender>
      <city>Portland</city>
      <country>US</country>
    </data>
    <data>
      <name>Ross Cobb</name>
      <hobby>Hiking</hobby>
      <age>21</age>
      <gender>M</gender>
      <city>Seattle</city>
      <country>US</country>
    </data>
    <data>
      <name>Nico Cordeiro</name>
      <hobby>Biking</hobby>
      <age>31</age>
      <gender>M</gender>
      <city>Vancouver</city>
      <country>Canada</country>
    </data>
    <data>
      <name>Emily Goe</name>
      <hobby>Hiking</hobby>
      <age>35</age>
      <gender>F</gender>
      <city>Seattle</city>
      <country>US</country>
    </data>
    <data>
      <name>Steinar Jennings</name>
      <hobby>Beer Brewing</hobby>
      <age>25</age>
      <gender>M</gender>
      <city>Istanbul</city>
      <country>Turkey</country>
    </data>
    <data>
      <name>Jordan Kroger</name>
      <hobby>Golfing</hobby>
      <age>45</age>
      <gender>M</gender>
      <city>Chicago</city>
      <country>US</country>
    </data>
    <data>
      <name>Jonathan Murphy</name>
      <hobby>Computer Programming</hobby>
      <age>25</age>
      <gender>M</gender>
      <city>Las Vegas</city>
      <country>US</country>
    </data>
    <data>
      <name>Sunanda Ramamurthi</name>
      <hobby>Reading</hobby>
      <age>35</age>
      <gender>F</gender>
      <city>Mumbai</city>
      <country>India</country>
    </data>
    <data>
      <name>Wenting Song</name>
      <hobby>Camping</hobby>
      <age>27</age>
      <gender>F</gender>
      <city>Bei Jing</city>
      <country>China</country>
    </data>
    <data>
      <name>Zachary Von Naumann</name>
      <hobby>Bowling</hobby>
      <age>29</age>
      <gender>M</gender>
      <city>Seattle</city>
      <country>US</country>
    </data>
    <data>
      <name>Ann Flynn</name>
      <hobby>Acting</hobby>
      <age>45</age>
      <gender>f</gender>
      <city>Seattle</city>
      <country>US</country>
    </data>
  </customers>